specmatch/__init__.py
specmatch/__main__.py
specmatch/audiofiles.py
specmatch/specmatch.glade
specmatch/spectrum.py
specmatch/ui.py
specmatch-0.10.0.data/data/share/applications/specmatch.desktop
specmatch-0.10.0.data/data/share/mime/packages/specmatch.xml
specmatch-0.10.0.data/data/share/icons/hicolor/scalable/apps/specmatch.svg
specmatch-0.10.0.dist-info/METADATA
specmatch-0.10.0.dist-info/WHEEL
specmatch-0.10.0.dist-info/entry_points.txt
specmatch-0.10.0.dist-info/licenses/LICENSE.md
specmatch-0.10.0.dist-info/RECORD
