Metadata-Version: 2.3
Name: specmatch
Version: 0.10.0
Summary: Calculate an IR to match a spectrum
Project-URL: Homepage, https://github.com/brummer10/SpecMatch
Project-URL: Bug Tracker, https://github.com/brummer10/SpecMatch/issues
License-Expression: MIT
License-File: LICENSE.md
Requires-Dist: matplotlib
Requires-Dist: numpy
Requires-Dist: pydub
Requires-Dist: pygobject
Requires-Dist: resampy
Requires-Dist: scipy
Requires-Dist: soundfile
